A2KA/A2KA.py
A2KA/SCNLS.py
A2KA/__init__.py
A2KA/utils.py
A2KA-0.1.7.dist-info/METADATA
A2KA-0.1.7.dist-info/WHEEL
A2KA-0.1.7.dist-info/top_level.txt
A2KA-0.1.7.dist-info/RECORD
