Metadata-Version: 2.1
Name: A2KA
Version: 0.1.7
Summary: Attention to Key Area, a plug and play interpretable network.
Home-page: https://github.com/Dsadd4/NLSExplorer_1.0/
Author: Yifan Li
Author-email: 2543179079@qq.com
Classifier: Programming Language :: Python :: 3
Classifier: License :: OSI Approved :: MIT License
Classifier: Operating System :: OS Independent
Requires-Python: >=3.7
